lscom/__init__.py
lscom/__main__.py
lscom/__version__.py
lscom/app.py
lscom-0.0.4.dist-info/licenses/LICENSE
lscom-0.0.4.dist-info/METADATA
lscom-0.0.4.dist-info/WHEEL
lscom-0.0.4.dist-info/entry_points.txt
lscom-0.0.4.dist-info/top_level.txt
lscom-0.0.4.dist-info/RECORD
