Metadata-Version: 2.4
Name: lscom
Version: 0.0.4
Summary: list available active COM ports
Home-page: https://github.com/joshschmelzle/lscom
Author: Josh Schmelzle
Author-email: josh@joshschmelzle.com
License: MIT
Keywords: com,com ports,serial
Classifier: Natural Language :: English
Classifier: Development Status :: 3 - Alpha
Classifier: Programming Language :: Python :: 3.2
Classifier: Intended Audience :: Developers
Classifier: Intended Audience :: System Administrators
Classifier: Topic :: Utilities
Requires-Python: >3.2,
License-File: LICENSE
Requires-Dist: pyserial
Dynamic: author
Dynamic: author-email
Dynamic: classifier
Dynamic: description
Dynamic: description-content-type
Dynamic: home-page
Dynamic: keywords
Dynamic: license
Dynamic: license-file
Dynamic: requires-dist
Dynamic: requires-python
Dynamic: summary
